CHANGES.rst
CONTRIBUTORS.rst
MANIFEST.in
README.rst
VERSION
VERSION_SUFFIX
setup.cfg
setup.py
docs/LICENSE.GPL
docs/LICENSE.rst
docs/index.rst
src/visaplan/__init__.py
src/visaplan/auto.msg
src/visaplan.zope.inputmacros.egg-info/PKG-INFO
src/visaplan.zope.inputmacros.egg-info/SOURCES.txt
src/visaplan.zope.inputmacros.egg-info/dependency_links.txt
src/visaplan.zope.inputmacros.egg-info/entry_points.txt
src/visaplan.zope.inputmacros.egg-info/namespace_packages.txt
src/visaplan.zope.inputmacros.egg-info/not-zip-safe
src/visaplan.zope.inputmacros.egg-info/requires.txt
src/visaplan.zope.inputmacros.egg-info/top_level.txt
src/visaplan/zope/__init__.py
src/visaplan/zope/inputmacros/__init__.py
src/visaplan/zope/inputmacros/configure.zcml
src/visaplan/zope/inputmacros/svn-commit.tmp
src/visaplan/zope/inputmacros/views/__init__.py
src/visaplan/zope/inputmacros/views/configure.zcml
src/visaplan/zope/inputmacros/views/formfields_div-base.pt
src/visaplan/zope/inputmacros/views/formfields_div.pt
src/visaplan/zope/inputmacros/views/formfields_table-base.pt
src/visaplan/zope/inputmacros/views/formfields_table.pt